{
  "title": "Virtual Barometric Pressure Sensor",
  "@context": "https://iot.mozilla.org/schemas",
  "@type": [
      "BarometricPressureSensor"
  ],
  "description": "",
  "href": "/things/virtual-things-29",
  "properties": {
      "pressure": {
          "name": "pressure",
          "value": 20,
          "title": "Pressure",
          "type": "number",
          "@type": "BarometricPressureProperty",
          "unit": "hectopascal",
          "minimum": 0,
          "readOnly": true,
          "forms": [
              {
                  "href": "/things/virtual-things-29/properties/pressure"
              }
          ]
      }
  },
  "actions": {},
  "events": {},
  "links": [
      {
          "rel": "alternate",
          "type": "text/html",
          "href": "/things/virtual-things-29"
      },
      {
          "rel": "alternate",
          "href": "ws://localhost:8080/things/virtual-things-29"
      }
  ],
  "forms": [
      {
          "href": "/things/virtual-things-29/properties",
          "op": "readallproperties"
      }
  ],
  "layoutIndex": 22,
  "selectedCapability": "BarometricPressureSensor",
  "iconHref": null,
  "group_id": null,
  "id": "http://localhost:8080/things/virtual-things-29",
  "base": "http://localhost:8080/",
  "securityDefinitions": {
      "oauth2_sc": {
          "scheme": "oauth2",
          "flow": "code",
          "authorization": "http://localhost:8080/oauth/authorize",
          "token": "http://localhost:8080/oauth/token",
          "scopes": [
              "/things/virtual-things-29:readwrite",
              "/things/virtual-things-29",
              "/things:readwrite",
              "/things"
          ]
      }
  },
  "security": "oauth2_sc"
}